{"success":true,"message":"Order created","data":{"id":3,"publicId":"bbd51320-61b8-4965-9723-251880bd3efe","orderNumber":"MOCK-2026-00001","status":"RESERVED","totalAmount":100.00,"subtotalAmount":100.00,"gstTotal":0,"gstRate":0,"gstTreatment":"NONE","gstRoundingAdjustment":0.00,"currency":"INR","dealerName":"Mock GST Dealer","traceId":null,"createdAt":1768378304.580668500,"items":[{"id":3,"productCode":"FG-GST","description":"Task-08 probe","quantity":1,"unitPrice":100.00,"lineSubtotal":100.00,"gstRate":0,"gstAmount":0,"lineTotal":100.00}]},"timestamp":1768378305.034436944}
HTTP_STATUS:200
